AUTHORS.rst
CONTRIBUTING.rst
HISTORY.rst
LICENSE
MANIFEST.in
README.rst
setup.py
ubuntufinder/__init__.py
ubuntufinder/actions.py
ubuntufinder/cli.py
ubuntufinder/exceptions.py
ubuntufinder/models.py
ubuntufinder/version.py
ubuntufinder.egg-info/PKG-INFO
ubuntufinder.egg-info/SOURCES.txt
ubuntufinder.egg-info/dependency_links.txt
ubuntufinder.egg-info/entry_points.txt
ubuntufinder.egg-info/not-zip-safe
ubuntufinder.egg-info/requires.txt
ubuntufinder.egg-info/top_level.txt