Metadata-Version: 1.0
Name: ubuntufinder
Version: 0.4.2
Summary: An utility package to locate the latest Ubuntu AMIs.
Home-page: https://github.com/krallin/ubuntufinder
Author: Thomas Orozco
Author-email: thomas@orozco.fr
License: BSD
Keywords: ubuntufinder
Platform: UNKNOWN
Classifier: Development Status :: 2 - Pre-Alpha
Classifier: Intended Audience :: Developers
Classifier: License :: OSI Approved :: BSD License
Classifier: Natural Language :: English
Classifier: Programming Language :: Python :: 2
Classifier: Programming Language :: Python :: 2.6
Classifier: Programming Language :: Python :: 2.7
Classifier: Programming Language :: Python :: 3
Classifier: Programming Language :: Python :: 3.3
